text_preprocessor/__init__.py
text_preprocessor/preprocessing.py
text_preprocessor/setup.py
text_preprocessor/utils.py
akeem_text_preprocessor-0.1.0.dist-info/METADATA
akeem_text_preprocessor-0.1.0.dist-info/WHEEL
akeem_text_preprocessor-0.1.0.dist-info/top_level.txt
akeem_text_preprocessor-0.1.0.dist-info/RECORD
